k_graph_kit/__init__.py
k_graph_kit/graph_class.py
k_graph_kit-0.0.1.dist-info/METADATA
k_graph_kit-0.0.1.dist-info/WHEEL
k_graph_kit-0.0.1.dist-info/licenses/LICENSE
k_graph_kit-0.0.1.dist-info/RECORD
