Metadata-Version: 2.1
Name: k_graph_kit
Version: 0.0.1
Summary: A package to easily deal with graph and their universe!
Project-URL: Homepage, https://pypi.org/project/k_graph_kit/
Project-URL: Issues, https://github.com/KpihX/k_graph_kit/issues
Project-URL: Repository, https://github.com/KpihX/k_graph_kit.git
Author-email: KpihX <kapoivha@gmail.com>
Maintainer-email: KpihX <kapoivha@gmail.com>
License: MIT License
License-File: LICENSE
Keywords: Djikstrat,Euler,Hamilton,chain,cycle,degree,graph,tree
Classifier: Development Status :: 4 - Beta
Classifier: Intended Audience :: Developers
Classifier: License :: OSI Approved :: MIT License
Classifier: Operating System :: OS Independent
Classifier: Programming Language :: Python :: 3
Requires-Python: >=3.8
